i18npy/Translator.py
i18npy/__init__.py
i18npy/helpers.py
i18npy/py.typed
i18npy-1.0.0.dist-info/LICENSE
i18npy-1.0.0.dist-info/WHEEL
i18npy-1.0.0.dist-info/METADATA
i18npy-1.0.0.dist-info/RECORD
