Metadata-Version: 2.1
Name: i18npy
Version: 1.0.0
Summary: Internationalization library. Python implementation of roddeh/i18njs
Home-page: https://github.com/marverix/i18npy
License: MIT
Keywords: i18n,i18npy,internationalization,translate,translation,translating
Author: Marek Sierociński
Author-email: mareksierocinski@gmail.com
Requires-Python: >=3.6,<4.0
Classifier: License :: OSI Approved :: MIT License
Classifier: Programming Language :: Python :: 3
Classifier: Programming Language :: Python :: 3.6
Classifier: Programming Language :: Python :: 3.7
Classifier: Programming Language :: Python :: 3.8
Classifier: Programming Language :: Python :: 3.9
Classifier: Topic :: Software Development :: Internationalization
Classifier: Topic :: Utilities
Project-URL: Repository, https://github.com/marverix/i18npy
